sqla2uml/__init__.py
sqla2uml/generator.py
sqla2uml/main.py
sqla2uml/scanner.py
sqla2uml-0.1.4.dist-info/LICENSE
sqla2uml-0.1.4.dist-info/METADATA
sqla2uml-0.1.4.dist-info/WHEEL
sqla2uml-0.1.4.dist-info/entry_points.txt
sqla2uml-0.1.4.dist-info/RECORD
