Metadata-Version: 2.1
Name: sqla2uml
Version: 0.1.4
Summary: Convert your SQLAlchemy models to UML diagrams (via PlantUML)
Home-page: https://github.com/abilian/sqla2uml
Author: Abilian SAS
Author-email: sf@abilian.com
Requires-Python: >=3.9,<4.0
Classifier: Development Status :: 3 - Alpha
Classifier: Intended Audience :: Developers
Classifier: Natural Language :: English
Classifier: Programming Language :: Python :: 3
Classifier: Programming Language :: Python :: 3.9
Classifier: Programming Language :: Python :: 3.10
Classifier: Programming Language :: Python :: 3.11
Classifier: Programming Language :: Python :: 3
Classifier: Programming Language :: Python :: 3.10
Classifier: Programming Language :: Python :: 3.11
Classifier: Programming Language :: Python :: 3.8
Classifier: Programming Language :: Python :: 3.9
Requires-Dist: SQLAlchemy (>=2.0.7)
Requires-Dist: click
Requires-Dist: devtools
